bt_tracker_utils/TrackerQueryException.py
bt_tracker_utils/__init__.py
bt_tracker_utils/check_tracker.py
bt_tracker_utils/query.py
bt_tracker_utils-0.1.3.dist-info/licenses/LICENSE
bt_tracker_utils-0.1.3.dist-info/METADATA
bt_tracker_utils-0.1.3.dist-info/WHEEL
bt_tracker_utils-0.1.3.dist-info/top_level.txt
bt_tracker_utils-0.1.3.dist-info/RECORD
