Metadata-Version: 2.4
Name: bt_tracker_utils
Version: 0.1.3
Summary: BitTorrent tracker utilities for checking availability and querying
Author: JackyHe398
Author-email: hekinghung@gmail.com
Requires-Python: >=3.6
License-File: LICENSE
Requires-Dist: requests>=2.32.4
Requires-Dist: bencodepy>=0.9.5
Requires-Dist: urllib3>=2.5.0
Dynamic: author
Dynamic: author-email
Dynamic: description
Dynamic: description-content-type
Dynamic: license-file
Dynamic: requires-dist
Dynamic: requires-python
Dynamic: summary
